[
  {
    "tag_name": "entity",
    "ids_to_tags": {
      "1": "B-battery_charge",
      "2": "I-battery_charge",
      "3": "L-battery_charge",
      "4": "U-battery_charge",
      "5": "B-battery_voltage",
      "6": "I-battery_voltage",
      "7": "L-battery_voltage",
      "8": "U-battery_voltage",
      "9": "B-charge_current",
      "10": "I-charge_current",
      "11": "L-charge_current",
      "12": "U-charge_current",
      "13": "B-condition_field",
      "14": "I-condition_field",
      "15": "L-condition_field",
      "16": "U-condition_field",
      "17": "B-condition_value",
      "18": "I-condition_value",
      "19": "L-condition_value",
      "20": "U-condition_value",
      "21": "B-field",
      "22": "I-field",
      "23": "L-field",
      "24": "U-field",
      "25": "B-frame_id",
      "26": "I-frame_id",
      "27": "L-frame_id",
      "28": "U-frame_id",
      "29": "B-logic_status",
      "30": "I-logic_status",
      "31": "L-logic_status",
      "32": "U-logic_status",
      "33": "B-maximum",
      "34": "I-maximum",
      "35": "L-maximum",
      "36": "U-maximum",
      "37": "B-start_time",
      "38": "I-start_time",
      "39": "L-start_time",
      "40": "U-start_time",
      "41": "B-stop_time",
      "42": "I-stop_time",
      "43": "L-stop_time",
      "44": "U-stop_time",
      "45": "B-target_field",
      "46": "I-target_field",
      "47": "L-target_field",
      "48": "U-target_field",
      "0": "O"
    },
    "tags_to_ids": {
      "B-battery_charge": 1,
      "I-battery_charge": 2,
      "L-battery_charge": 3,
      "U-battery_charge": 4,
      "B-battery_voltage": 5,
      "I-battery_voltage": 6,
      "L-battery_voltage": 7,
      "U-battery_voltage": 8,
      "B-charge_current": 9,
      "I-charge_current": 10,
      "L-charge_current": 11,
      "U-charge_current": 12,
      "B-condition_field": 13,
      "I-condition_field": 14,
      "L-condition_field": 15,
      "U-condition_field": 16,
      "B-condition_value": 17,
      "I-condition_value": 18,
      "L-condition_value": 19,
      "U-condition_value": 20,
      "B-field": 21,
      "I-field": 22,
      "L-field": 23,
      "U-field": 24,
      "B-frame_id": 25,
      "I-frame_id": 26,
      "L-frame_id": 27,
      "U-frame_id": 28,
      "B-logic_status": 29,
      "I-logic_status": 30,
      "L-logic_status": 31,
      "U-logic_status": 32,
      "B-maximum": 33,
      "I-maximum": 34,
      "L-maximum": 35,
      "U-maximum": 36,
      "B-start_time": 37,
      "I-start_time": 38,
      "L-start_time": 39,
      "U-start_time": 40,
      "B-stop_time": 41,
      "I-stop_time": 42,
      "L-stop_time": 43,
      "U-stop_time": 44,
      "B-target_field": 45,
      "I-target_field": 46,
      "L-target_field": 47,
      "U-target_field": 48,
      "O": 0
    },
    "num_tags": 49
  }
]